nectarpy/__init__.py
nectarpy/lib.py
nectarpy/lib_v1.py
nectarpy/common/__init__.py
nectarpy/common/blockchain_init.py
nectarpy/common/encryption.py
nectarpy/config/EoaBond.json
nectarpy/config/QueryManager.json
nectarpy/config/USDC.json
nectarpy/config/UserRole.json
nectarpy/config/blockchain.json
nectarpy/config/starnode.json
nectarpy-0.15.1.dist-info/licenses/LICENSE
nectarpy-0.15.1.dist-info/licenses/NOTICE
nectarpy-0.15.1.dist-info/METADATA
nectarpy-0.15.1.dist-info/WHEEL
nectarpy-0.15.1.dist-info/top_level.txt
nectarpy-0.15.1.dist-info/RECORD
